trollius/__init__.py
trollius/_overlapped.pyd
trollius/base_events.py
trollius/base_subprocess.py
trollius/compat.py
trollius/constants.py
trollius/coroutines.py
trollius/events.py
trollius/executor.py
trollius/futures.py
trollius/locks.py
trollius/log.py
trollius/proactor_events.py
trollius/protocols.py
trollius/py27_weakrefset.py
trollius/py33_exceptions.py
trollius/py33_winapi.py
trollius/py3_ssl.py
trollius/queues.py
trollius/selector_events.py
trollius/selectors.py
trollius/sslproto.py
trollius/streams.py
trollius/subprocess.py
trollius/tasks.py
trollius/test_support.py
trollius/test_utils.py
trollius/time_monotonic.py
trollius/transports.py
trollius/unix_events.py
trollius/windows_events.py
trollius/windows_utils.py
trollius-2.2.1.dist-info/AUTHORS
trollius-2.2.1.dist-info/COPYING
trollius-2.2.1.dist-info/METADATA
trollius-2.2.1.dist-info/WHEEL
trollius-2.2.1.dist-info/top_level.txt
trollius-2.2.1.dist-info/RECORD
